eclabfiles/__init__.py
eclabfiles/main.py
eclabfiles/mpr.py
eclabfiles/mps.py
eclabfiles/mpt.py
eclabfiles/techniques.py
eclabfiles-0.4.1.dist-info/LICENSE
eclabfiles-0.4.1.dist-info/METADATA
eclabfiles-0.4.1.dist-info/WHEEL
eclabfiles-0.4.1.dist-info/top_level.txt
eclabfiles-0.4.1.dist-info/RECORD
