Metadata-Version: 2.1
Name: eclabfiles
Version: 0.4.1
Summary: Processing and converting of data files from BioLogic's EC-Lab.
Home-page: https://github.com/vetschn/eclabfiles
Author: Nicolas Vetsch
Author-email: vetschnicolas@gmail.com
License: UNKNOWN
Project-URL: Bug Tracker, https://github.com/vetschn/eclabfiles/issues
Keywords: mpt,mpr,mps,biologic,ec-lab
Platform: UNKNOWN
Classifier: Intended Audience :: Developers
Classifier: Intended Audience :: Science/Research
Classifier: License :: OSI Approved :: GNU General Public License v3 or later (GPLv3+)
Classifier: Programming Language :: Python :: 3 :: Only
Classifier: Operating System :: OS Independent
Classifier: Topic :: Scientific/Engineering
Requires-Python: >=3.9
License-File: LICENSE
Requires-Dist: numpy
Requires-Dist: pandas
Requires-Dist: openpyxl
